nider/__init__.py
nider/core.py
nider/exceptions.py
nider/models.py
nider/tools.py
nider/utils.py
nider/colors/__init__.py
nider/colors/colormap.py
nider/colors/utils.py
nider/mixins/__init__.py
nider/mixins/img_components_mixins.py
nider/mixins/text_mixins.py
nider-0.5.0.dist-info/AUTHORS.rst
nider-0.5.0.dist-info/LICENSE
nider-0.5.0.dist-info/METADATA
nider-0.5.0.dist-info/WHEEL
nider-0.5.0.dist-info/top_level.txt
nider-0.5.0.dist-info/RECORD
