Metadata-Version: 1.1
Name: nider
Version: 0.5.0
Summary: Python package to add text to images, textures and different backgrounds
Home-page: https://github.com/pythad/nider
Author: Vladyslav Ovchynnykov
Author-email: ovd4mail@gmail.com
License: MIT license
Keywords: nider
Platform: UNKNOWN
Classifier: Development Status :: 5 - Production/Stable
Classifier: Intended Audience :: Developers
Classifier: License :: OSI Approved :: MIT License
Classifier: Natural Language :: English
Classifier: Programming Language :: Python :: 3
Classifier: Programming Language :: Python :: 3.4
Classifier: Programming Language :: Python :: 3.5
Classifier: Programming Language :: Python :: 3.6
